av1_scd/__init__.py
av1_scd/__main__.py
av1_scd/cfg.py
av1_scd/keyframes.py
av1_scd/log.py
av1_scd/main.py
av1_scd/mediainfo.py
av1_scd/option.py
av1_scd/predefined.py
av1_scd/scd/avscenechange.py
av1_scd/scd/ffmpeg.py
av1_scd/scd/pyscene.py
av1_scd/scd/transnetv2.py
av1_scd/scd/vsxvid.py
av1_scd/util.py
av1_scd/validate.py
av1_scd-3.0.1.dist-info/licenses/LICENSE
av1_scd-3.0.1.dist-info/WHEEL
av1_scd-3.0.1.dist-info/entry_points.txt
av1_scd-3.0.1.dist-info/METADATA
av1_scd-3.0.1.dist-info/RECORD
