Metadata-Version: 2.4
Name: av1-scd
Version: 3.0.1
Summary: Tool to quickly detect scene change and generate config file for encoder to force keyframe for Encoding video.
Author: Khaoklong
Author-email: Khaoklong <chatmongkol.long@gmail.com>
License-Expression: MIT
License-File: LICENSE
Classifier: Programming Language :: Python :: 3.12
Classifier: Programming Language :: Python :: 3.13
Classifier: Operating System :: OS Independent
Classifier: License :: OSI Approved :: MIT License
Classifier: Environment :: Console
Classifier: Development Status :: 5 - Production/Stable
Requires-Dist: colorama>=0.4.6
Requires-Dist: numpy>=2.2.6
Requires-Dist: opencv-python>=4.12.0.88
Requires-Dist: pymediainfo>=7.0.1
Requires-Dist: scenedetect<0.7
Requires-Dist: termcolor>=3.1.0
Requires-Dist: tqdm>=4.67.1
Requires-Dist: av>=15.0.0 ; extra == 'pyscene'
Requires-Dist: moviepy>=2.2.1 ; extra == 'pyscene'
Requires-Dist: onnxruntime>=1.22.1 ; extra == 'transnet'
Requires-Dist: onnxruntime-gpu>=1.22.0 ; extra == 'transnet'
Requires-Dist: vapoursynth>=71 ; extra == 'vsxvid'
Requires-Dist: vsjetpack>=0.8.2 ; extra == 'vsxvid'
Requires-Python: >=3.12
Project-URL: Homepage, https://github.com/Khaoklong51/av1-scd/
Project-URL: Issues, https://github.com/Khaoklong51/av1-scd/issues
Provides-Extra: pyscene
Provides-Extra: transnet
Provides-Extra: vsxvid
